prompt4all/__init__.py
prompt4all/app.py
prompt4all/common.py
prompt4all/context.py
prompt4all/gradio_chatbot_patch.py
prompt4all/gradio_css.py
prompt4all/theme.py
prompt4all/api/__init__.py
prompt4all/api/base_api.py
prompt4all/api/context_type.py
prompt4all/api/message.py
prompt4all/examples/query_database/README.md
prompt4all/examples/query_database/schema_V2.sql
prompt4all/examples/query_database/schema_old.sql
prompt4all/images/blocks_summary.png
prompt4all/images/dalle2_1.png
prompt4all/images/dark1.png
prompt4all/images/enviorvariables.png
prompt4all/images/query_database.png
prompt4all/images/query_sql_flow.png
prompt4all/images/rewrite1.png
prompt4all/images/ui_1.png
prompt4all/images/ui_2.png
prompt4all/prompts/dalle2.md
prompt4all/prompts/dalle3.md
prompt4all/prompts/incremental_rolling_summary.md
prompt4all/prompts/meeting_minutes_summary.md
prompt4all/prompts/mindmap_summary.md
prompt4all/prompts/parallel_chunks_summary.md
prompt4all/prompts/rolling_summary.md
prompt4all/prompts/summary_final_cleansing.md
prompt4all/prompts/topic_driven_summary.md
prompt4all/tools/__init__.py
prompt4all/tools/code_interpreter.json
prompt4all/tools/code_interpreter.py
prompt4all/tools/database_tools.py
prompt4all/tools/image_generation.json
prompt4all/tools/query_sql.json
prompt4all/tools/tool_icons/query_sql.png
prompt4all/tools/tool_icons/search_web.png
prompt4all/utils/__init__.py
prompt4all/utils/chatgpt_utils.py
prompt4all/utils/database_utils.py
prompt4all/utils/io_utils.py
prompt4all/utils/pdf_utils.py
prompt4all/utils/regex_utils.py
prompt4all/utils/summary_utils.py
prompt4all/utils/tokens_utils.py
prompt4all/utils/web_utils.py
prompt4all/utils/whisper_utils.py
prompt4all-0.0.7.dist-info/LICENSE
prompt4all-0.0.7.dist-info/METADATA
prompt4all-0.0.7.dist-info/WHEEL
prompt4all-0.0.7.dist-info/top_level.txt
prompt4all-0.0.7.dist-info/RECORD
