Metadata-Version: 2.1
Name: prompt4all
Version: 0.0.7
Summary: Prompt is all you need
Download-URL: https://test.pypi.org/project/prompt4all
Author: Allan Yiin
Author-email: allanyiin.ai@gmail.com
License: MIT
Keywords: chatgpt,gpt4
Classifier: Development Status :: 4 - Beta
Classifier: Intended Audience :: Developers
Classifier: Intended Audience :: Education
Classifier: Intended Audience :: Science/Research
Classifier: License :: OSI Approved :: MIT License
Classifier: Programming Language :: Python :: 3.7
Classifier: Programming Language :: Python :: 3.8
Classifier: Programming Language :: Python :: 3.9
Classifier: Topic :: Software Development :: Libraries
Classifier: Topic :: Software Development :: Libraries :: Python Modules
Requires-Python: >=3.7
License-File: LICENSE
Requires-Dist: gradio (>=4.7.1)
Requires-Dist: regex (>=2022.10.31)
Requires-Dist: openai (>=1.1.1)
Requires-Dist: requests (>=2.28.1)
Requires-Dist: pillow (>=9.4.0)
Requires-Dist: beautifulsoup4 (>=4.11.1)
Requires-Dist: numpy (>=1.23.5)
Requires-Dist: opencv-python (>=4.7.0.68)
Requires-Dist: markdown2 (>=2.4.8)
Requires-Dist: tiktoken (>=0.3.3)
Requires-Dist: asyncio (>=3.4.3)
Requires-Dist: whisper (>=1.1.10)
Requires-Dist: pydub (>=0.25.1)
Requires-Dist: Markdown (~=3.4.1)
Requires-Dist: soundfile (~=0.12.1)
Requires-Dist: torch (~=2.0.1)
Requires-Dist: pandas (~=1.5.2)
Requires-Dist: pathlib (~=1.0.1)
Requires-Dist: tqdm (~=4.64.1)
Requires-Dist: setuptools (~=67.8.0)
Requires-Dist: SQLAlchemy (>=2.0.0)
Requires-Dist: prompt4all (~=0.0.6)
Requires-Dist: pyodbc
Provides-Extra: tests
Requires-Dist: pytest ; extra == 'tests'
Requires-Dist: pytest-pep8 ; extra == 'tests'
Requires-Dist: pytest-xdist ; extra == 'tests'
Requires-Dist: pytest-cov ; extra == 'tests'
Requires-Dist: requests ; extra == 'tests'
Requires-Dist: markdown ; extra == 'tests'
